censtats/__init__.py
censtats/common.py
censtats/main.py
censtats/entropy/__init__.py
censtats/entropy/cli.py
censtats/entropy/constants.py
censtats/length/__init__.py
censtats/length/cli.py
censtats/length/constants.py
censtats/length/estimate_length.py
censtats/length/io.py
censtats/nonredundant/__init__.py
censtats/nonredundant/cli.py
censtats/nonredundant/constants.py
censtats/self_ident/__init__.py
censtats/self_ident/cli.py
censtats/self_ident/estimate_identity.py
censtats/self_ident/read_fasta.py
censtats-0.1.2.dist-info/licenses/LICENSE
censtats-0.1.2.dist-info/METADATA
censtats-0.1.2.dist-info/WHEEL
censtats-0.1.2.dist-info/entry_points.txt
censtats-0.1.2.dist-info/top_level.txt
censtats-0.1.2.dist-info/RECORD
