Metadata-Version: 2.4
Name: CenStats
Version: 0.1.2
Summary: Centromere statistics toolkit.
Author-email: Keith Oshima <oshimak@pennmedicine.upenn.edu>
License: MIT License
Project-URL: Homepage, https://github.com/logsdon-lab/CenStats
Requires-Python: >=3.12
License-File: LICENSE
Requires-Dist: polars>=1.19.0
Requires-Dist: loguru>=0.7.2
Requires-Dist: intervaltree>=3.1.0
Requires-Dist: matplotlib>=3.10.0
Requires-Dist: mmh3>=5.0.1
Requires-Dist: pyfaidx>=0.8.1.4
Requires-Dist: numpy>=2.2.1
Dynamic: license-file
